LICENSE
deafadder_container/ContainerException.py
deafadder_container/MetaTemplate.py
deafadder_container/Wiring.py
deafadder_container/__init__.py
deafadder_container-0.5.0.dist-info/LICENSE
deafadder_container-0.5.0.dist-info/WHEEL
deafadder_container-0.5.0.dist-info/METADATA
deafadder_container-0.5.0.dist-info/RECORD
