Metadata-Version: 2.1
Name: deafadder-container
Version: 0.5.0
Summary: A dependency injection tools and container manager for python
Home-page: https://github.com/deaf-adder/deafadder-container
License: MIT
Keywords: component,autowire,DI,singleton
Author: Leddzip
Author-email: leddzip@gmail.com
Requires-Python: >=3.8,<4.0
Classifier: License :: OSI Approved :: MIT License
Classifier: Programming Language :: Python :: 3
Classifier: Programming Language :: Python :: 3.8
Classifier: Programming Language :: Python :: 3.9
Project-URL: Repository, https://github.com/deaf-adder/deafadder-container
